[{"error":"FAULTY 0% DRINK","drink":{"name":"Korven Kutsu Wild Spruce Lager","producer":"Korven Kutsu","ean":"6429810225450","link":"https://www.s-kaupat.fi/tuote/6429810225450","price":3.99,"percentage":null,"imageLink":"https://cdn.s-cloud.fi/v1/w750_q75/product/ean/6429810225450_kuva1.jpg","category":"Oluet","size":0.5,"store":"skaupat"}},{"error":"FAULTY 0% DRINK","drink":{"name":"Korven Kutsu Classic Lager","producer":"Korven Kutsu","ean":"6429810225160","link":"https://www.s-kaupat.fi/tuote/6429810225160","price":3.59,"percentage":null,"imageLink":"https://cdn.s-cloud.fi/v1/w750_q75/product/ean/6429810225160_kuva1.jpg","category":"Oluet","size":0.5,"store":"skaupat"}},{"error":"FAULTY 0% DRINK","drink":{"name":"Hailuotolainen luomuolut Laakeri","producer":"Hailuodon Panimo","ean":"6430066990016","link":"https://www.s-kaupat.fi/tuote/6430066990016","price":8.49,"percentage":null,"imageLink":"https://cdn.s-cloud.fi/v1/w750_q75/product/ean/6430066990016_kuva1.jpg","category":"Oluet","size":0.5,"store":"skaupat"}},{"error":"FAULTY 0% DRINK","drink":{"name":"Ukko-Pekka kotikaljan makuinen hiilihapollinen juoma 1,5 l","producer":"Ukko-Pekka","ean":"6416884207130","link":"https://www.s-kaupat.fi/tuote/6416884207130","price":3.19,"percentage":null,"imageLink":"https://cdn.s-cloud.fi/v1/w750_q75/product/ean/6416884207130_kuva1.jpg","category":"Oluet","size":1.5,"store":"skaupat"}},{"error":"FAULTY 0% DRINK","drink":{"name":"Tuoppi Kotikalja gluteeniton 0,75 L","producer":"Tuoppi","ean":"6421000230008","link":"https://www.s-kaupat.fi/tuote/6421000230008","price":3.3,"percentage":null,"imageLink":"https://cdn.s-cloud.fi/v1/w750_q75/product/ean/6421000230008_kuva1.jpg","category":"Oluet","size":0.75,"store":"skaupat"}},{"error":"FAULTY 0% DRINK","drink":{"name":"Berliner Kindl Jubiläums Pilsener 0,5 l olut tlk","producer":"Berliner Kindl","ean":"4053400206349","link":"https://www.s-kaupat.fi/tuote/4053400206349","price":3.29,"percentage":null,"imageLink":"https://cdn.s-cloud.fi/v1/w750_q75/product/ean/4053400206349_kuva1.jpg","category":"Oluet","size":0.5,"store":"skaupat"}},{"error":"FAULTY 0% DRINK","drink":{"name":"Super Sour","producer":"CoolHead","ean":"6438560001191","link":"https://www.s-kaupat.fi/tuote/6438560001191","price":4.29,"percentage":null,"imageLink":"https://cdn.s-cloud.fi/v1/w750_q75/product/ean/6438560001191_kuva1.jpg","category":"Oluet","size":0.5,"store":"skaupat"}},{"error":"FAULTY 0% DRINK","drink":{"name":"Red & Black","producer":"CoolHead","ean":"6438560001139","link":"https://www.s-kaupat.fi/tuote/6438560001139","price":4.29,"percentage":null,"imageLink":"https://cdn.s-cloud.fi/v1/w750_q75/product/ean/6438560001139_kuva1.jpg","category":"Oluet","size":0.33,"store":"skaupat"}},{"error":"FAULTY 0% DRINK","drink":{"name":"Sonnisaari Mulkero Porter 0,33l pienpanimo-olut","producer":"Sonnisaari","ean":"6430064450451","link":"https://www.s-kaupat.fi/tuote/6430064450451","price":3.99,"percentage":null,"imageLink":"https://cdn.s-cloud.fi/v1/w750_q75/product/ean/6430064450451_kuva1.jpg","category":"Oluet","size":0.33,"store":"skaupat"}},{"error":"FAULTY 0% DRINK","drink":{"name":"CoolHead FestBier","producer":"CoolHead Brew","ean":"6438560002075","link":"https://www.s-kaupat.fi/tuote/6438560002075","price":4.24,"percentage":null,"imageLink":"https://cdn.s-cloud.fi/v1/w750_q75/product/ean/6438560002075_kuva1.jpg","category":"Oluet","size":0.33,"store":"skaupat"}},{"error":"FAULTY 0% DRINK","drink":{"name":"Tuoppi Kotikalja mallasjuomauute 3x35g","producer":"Tuoppi","ean":"6421000050002","link":"https://www.s-kaupat.fi/tuote/6421000050002","price":1.99,"percentage":null,"imageLink":"https://cdn.s-cloud.fi/v1/w750_q75/product/ean/6421000050002_kuva1.jpg","category":"Oluet","size":0.99,"store":"skaupat"}},{"error":"FAULTY 0% DRINK","drink":{"name":"Crowmoor Extra Dry Apple siideri  33 cl tlk 6-pack","producer":"Crowmoor","ean":"6415600539043","link":"https://www.s-kaupat.fi/tuote/6415600539043","price":13.98,"percentage":null,"imageLink":"https://cdn.s-cloud.fi/v1/w750_q75/product/ean/6415600539043_kuva1.jpg","category":"Siiderit","size":1.98,"store":"skaupat"}},{"error":"FAULTY 0% DRINK","drink":{"name":"Crowmoor Dry Apple 33 cl tlk 6-pack","producer":"Crowmoor","ean":"6415600510110","link":"https://www.s-kaupat.fi/tuote/6415600510110","price":13.98,"percentage":null,"imageLink":"https://cdn.s-cloud.fi/v1/w750_q75/product/ean/6415600510110_kuva1.jpg","category":"Siiderit","size":1.98,"store":"skaupat"}},{"error":"FAULTY 0% DRINK","drink":{"name":"Kyrö Ginger Long Drink","producer":"Kyrö Distillery Company","ean":"6430055041378","link":"https://www.s-kaupat.fi/tuote/6430055041378","price":2.95,"percentage":null,"imageLink":"https://cdn.s-cloud.fi/v1/w750_q75/product/ean/6430055041378_kuva1.jpg","category":"Juomasekoitukset ja lonkerot","size":0.33,"store":"skaupat"}},{"error":"FAULTY 0% DRINK","drink":{"name":"Kyrö Blueberry Long Drink","producer":"Kyrö Distillery Company","ean":"6430055041354","link":"https://www.s-kaupat.fi/tuote/6430055041354","price":1.55,"percentage":null,"imageLink":"https://cdn.s-cloud.fi/v1/w750_q75/product/ean/6430055041354_kuva1.jpg","category":"Juomasekoitukset ja lonkerot","size":1.98,"store":"skaupat"}},{"error":"FAULTY 0% DRINK","drink":{"name":"Smirnoff Ice Original juomasekoitus 0,275 L","producer":"Smirnoff Ice","ean":"5410316983693","link":"https://www.s-kaupat.fi/tuote/5410316983693","price":2.99,"percentage":null,"imageLink":"https://cdn.s-cloud.fi/v1/w750_q75/product/ean/5410316983693_kuva1.jpg","category":"Juomasekoitukset ja lonkerot","size":0.275,"store":"skaupat"}},{"error":"FAULTY 0% DRINK","drink":{"name":"Smirnoff Ice Raspberry juomasekoitus 0,275 L","producer":"Smirnoff Ice","ean":"5410316965583","link":"https://www.s-kaupat.fi/tuote/5410316965583","price":3.2,"percentage":null,"imageLink":"https://cdn.s-cloud.fi/v1/w750_q75/product/ean/5410316965583_kuva1.jpg","category":"Juomasekoitukset ja lonkerot","size":0.275,"store":"skaupat"}},{"error":"FAULTY 0% DRINK","drink":{"name":"Smirnoff Ice Tropical juomasekoitus  0,275 L","producer":"Smirnoff Ice","ean":"5410316962094","link":"https://www.s-kaupat.fi/tuote/5410316962094","price":3.2,"percentage":null,"imageLink":"https://cdn.s-cloud.fi/v1/w750_q75/product/ean/5410316962094_kuva1.jpg","category":"Juomasekoitukset ja lonkerot","size":0.275,"store":"skaupat"}},{"error":"FAULTY 0% DRINK","drink":{"name":"Liviko Cooler Dark Cherry 27,5cl","producer":"Cooler","ean":"4740050005209","link":"https://www.s-kaupat.fi/tuote/4740050005209","price":2.49,"percentage":null,"imageLink":"https://cdn.s-cloud.fi/v1/w750_q75/product/ean/4740050005209_kuva1.jpg","category":"Juomasekoitukset ja lonkerot","size":0.075,"store":"skaupat"}},{"error":"FAULTY 0% DRINK","drink":{"name":"Smirnoff Ice Blue juomasekoitus  0,275 L","producer":"Smirnoff Ice","ean":"5410316951227","link":"https://www.s-kaupat.fi/tuote/5410316951227","price":3.2,"percentage":null,"imageLink":"https://cdn.s-cloud.fi/v1/w750_q75/product/ean/5410316951227_kuva1.jpg","category":"Juomasekoitukset ja lonkerot","size":0.275,"store":"skaupat"}},{"error":"FAULTY 0% DRINK","drink":{"name":"KontioMehu Lehtikuohu 0,75 l","producer":"Lehtikuohu","ean":"6418369001004","link":"https://www.s-kaupat.fi/tuote/6418369001004","price":13.99,"percentage":null,"imageLink":"https://cdn.s-cloud.fi/v1/w750_q75/product/ean/6418369001004_kuva1.jpg","category":"Muut viinit","size":0.75,"store":"skaupat"}},{"error":"FAULTY 0% DRINK","drink":{"name":"KontioMehu Lehtikuohu 0,2 l","producer":"Lehtikuohu","ean":"6418369001011","link":"https://www.s-kaupat.fi/tuote/6418369001011","price":4.59,"percentage":null,"imageLink":"https://cdn.s-cloud.fi/v1/w750_q75/product/ean/6418369001011_kuva1.jpg","category":"Muut viinit","size":0.2,"store":"skaupat"}},{"error":"FAULTY 0% DRINK","drink":{"name":"Jacob's Creek UnVined Riesling 75 cl","producer":"Jacob's Creek","ean":"9300727016287","link":"https://www.s-kaupat.fi/tuote/9300727016287","price":7.29,"percentage":null,"imageLink":"https://cdn.s-cloud.fi/v1/w750_q75/product/ean/9300727016287_kuva1.jpg","category":"Muut viinit","size":0.75,"store":"skaupat"}},{"error":"FAULTY 0% DRINK","drink":{"name":"ÖUN Raparperi-kuusikuohujuoma luomu 75cl","producer":"Öun Drinks","ean":"4744317010319","link":"https://www.s-kaupat.fi/tuote/4744317010319","price":8.49,"percentage":null,"imageLink":"https://cdn.s-cloud.fi/v1/w750_q75/product/ean/4744317010319_kuva1.jpg","category":"Muut viinit","size":0.75,"store":"skaupat"}},{"error":"FAULTY 0% DRINK","drink":{"name":"Cosmopolitan Diva Berry Fusion aromatiosoitu kuohuviini","producer":"Cosmopolitan","ean":"4750012030859","link":"https://www.s-kaupat.fi/tuote/4750012030859","price":8.95,"percentage":null,"imageLink":"https://cdn.s-cloud.fi/v1/w750_q75/product/ean/4750012030859_kuva1.jpg","category":"Muut viinit","size":0.75,"store":"skaupat"}},{"error":"FAULTY 0% DRINK","drink":{"name":"Chateau del ISH Sparkling Rosé 25cl","producer":"ISH","ean":"5715008106443","link":"https://www.s-kaupat.fi/tuote/5715008106443","price":1.75,"percentage":null,"imageLink":"https://cdn.s-cloud.fi/v1/w750_q75/product/ean/5715008106443_kuva1.jpg","category":"Muut viinit","size":0.25,"store":"skaupat"}},{"error":"FAULTY 0% DRINK","drink":{"name":"Corvers-Kauter R3 Rhein Riesling Zero 0,75 L","producer":"Corvers-Kauter","ean":"4036198000009","link":"https://www.s-kaupat.fi/tuote/4036198000009","price":5.55,"percentage":null,"imageLink":"https://cdn.s-cloud.fi/v1/w750_q75/product/ean/4036198000009_kuva1.jpg","category":"Muut viinit","size":0.75,"store":"skaupat"}},{"error":"MISSING FIELD \"size","drink":{"name":"Lahjakortti","productCode":"833310","link":"https://www.alko.fi/tuotteet/833310/","price":1,"imageLink":"https://images.alko.fi/images/cs_srgb,f_auto,t_medium/cdn/833310/Lahjakortti","category":"Ei tietoa","size":null,"store":"alko"}},{"error":"MISSING FIELD \"size","drink":{"name":"Stallhagen Delikat olut 4,7% 0,355l tlk","producer":"STALLHAGEN","ean":"6430018523729","link":"https://www.k-ruoka.fi/kauppa/tuote/stallhagen-delikat-olut-47-0355l-tlk-6430018523729","price":32.28,"percentage":4.7,"imageLink":"https://public.keskofiles.com/f/k-ruoka/product/6430018523729","category":"Oluet","store":"kruoka"}},{"error":"MISSING FIELD \"size","drink":{"name":"Stallhagen Original Lager 4,5% 0,355 tlk","producer":"STALLHAGEN","ean":"6430018523699","link":"https://www.k-ruoka.fi/kauppa/tuote/stallhagen-original-lager-45-0355-tlk-6430018523699","price":31.08,"percentage":4.5,"imageLink":"https://public.keskofiles.com/f/k-ruoka/product/6430018523699","category":"Oluet","store":"kruoka"}}]